loql/__init__.py
loql/__main__.py
loql/app.py
loql/cli.py
loql/style.tcss
loql/views.py
loql-1.0.0.dist-info/LICENSE
loql-1.0.0.dist-info/METADATA
loql-1.0.0.dist-info/WHEEL
loql-1.0.0.dist-info/entry_points.txt
loql-1.0.0.dist-info/RECORD
