Metadata-Version: 2.1
Name: LoQL
Version: 1.0.0
Summary: Terminal based SQL client for local data
Home-page: https://github.com/dannyboland/loql
License: MIT
Author: Danny Boland
Author-email: danny@boland.dev
Requires-Python: >=3.11,<4.0
Classifier: Development Status :: 5 - Production/Stable
Classifier: Environment :: Console
Classifier: Intended Audience :: Developers
Classifier: Intended Audience :: Information Technology
Classifier: Intended Audience :: Science/Research
Classifier: License :: OSI Approved :: MIT License
Classifier: Natural Language :: English
Classifier: Programming Language :: Python :: 3
Classifier: Programming Language :: Python :: 3.11
Classifier: Programming Language :: Python :: 3.12
Classifier: Topic :: Database
Classifier: Topic :: Utilities
Classifier: Typing :: Typed
Requires-Dist: duckdb (>=1.0,<2.0)
Requires-Dist: openpyxl (>=3.1.5,<4.0.0)
Requires-Dist: pandas (>=2.2,<3.0)
Requires-Dist: pyarrow (>=17.0,<18.0)
Requires-Dist: textual[syntax] (>=0.73.0,<0.74.0)
Requires-Dist: xlrd (>=2.0.1,<3.0.0)
